{"ApprovalTime": "2016-03-10T17:20:29Z", "AutoApprovalTime": "2016-03-10T17:19:31Z", "AssignmentId": "3VFJCI1K4ZZV22UVR2SXM9UBNF5RGQ", "WorkerId": "anon362", "answers": {"data": {"wtp_g": ["$"], "race_ethn": ["white"], "engl": ["Yes"], "wtp_b": ["$10"], "age": ["25"], "hh": ["2"], "comments": [""], "beer": ["4"], "income": ["4"], "gen": ["Female"]}}, "AcceptTime": "2016-03-10T17:14:03Z", "HITId": "3Z56AA6EK40ZL9U4KEITZZRQD1Z6MY", "Assignment": "", "AssignmentStatus": "Approved", "SubmitTime": "2016-03-10T17:14:31Z"}