{
    "ApprovalTime": "2016-03-10T18:15:28Z",
    "AutoApprovalTime": "2016-03-10T18:12:50Z",
    "AssignmentId": "3ATPCQ38J8A3PCTEJXSHYJC5S7FYAV",
    "WorkerId": "A3EWTW55UCNAHG",
    "answers": {
        "data": {
            "wtp_g": [
                "$"
            ],
            "race_ethn": [
                "white"
            ],
            "engl": [
                "Yes"
            ],
            "wtp_b": [
                "$10"
            ],
            "age": [
                "23"
            ],
            "beer": [
                "1"
            ],
            "comments": [
                "Nope."
            ],
            "hh": [
                "1"
            ],
            "income": [
                "2"
            ],
            "gen": [
                "Male"
            ]
        }
    },
    "AcceptTime": "2016-03-10T18:06:55Z",
    "HITId": "3Z56AA6EK40ZL9U4KEITZZRQD1Z6MY",
    "Assignment": "",
    "AssignmentStatus": "Approved",
    "SubmitTime": "2016-03-10T18:07:50Z"
}